{
  "controls": {
    "checkBox": 0,
    "spinner": 1,
    "choiceBox": 2
  },
  "modbusFunctionCodes": {
    "readCoils": 1,
    "readHoldingRegisters": 3,
    "writeMultipleCoils": 9,
    "writeMultipleRegisters": 10
  },
  "actuators": [
    {
      "name": "Приточный вентилятор",
      "attributes": [
        {
          "name": "В работе",
          "control": 0,
          "minValue": 0,
          "maxValue": 1,
          "modbusParameters": {
            "address": 5418,
            "varType": "BOOL"
          }
        },
        {
          "name": "Задержка РПД",
          "control": 1,
          "minValue": 0,
          "maxValue": 300,
          "modbusParameters": {
            "address": 5417,
            "varType": "UINT8"
          }
        },
        {
          "name": "Min U, %",
          "control": 1,
          "minValue": 0,
          "maxValue": 100,
          "modbusParameters": {
            "address": 5415,
            "varType": "UINT8"
          }
        },
        {
          "name": "Nom U, %",
          "control": 1,
          "minValue": 0,
          "maxValue": 100,
          "modbusParameters": {
            "address": 5414,
            "varType": "UINT8"
          }
        },
        {
          "name": "Max U, %",
          "control": 1,
          "minValue": 0,
          "maxValue": 100,
          "modbusParameters": {
            "address": 5416,
            "varType": "UINT8"
          }
        }
      ]
    }
  ]
}
